common_stats/__init__.py
common_stats/statistics.py
common_stats_pratikxxx/__init__.py
common_stats_pratikxxx/statistics.py
common_stats_pratikxxx-0.0.1.dist-info/licenses/LICENSE
test/__init__.py
test/test_statistics.py
common_stats_pratikxxx-0.0.1.dist-info/METADATA
common_stats_pratikxxx-0.0.1.dist-info/WHEEL
common_stats_pratikxxx-0.0.1.dist-info/top_level.txt
common_stats_pratikxxx-0.0.1.dist-info/RECORD
